fede.py
fede-0.1.1.dist-info/entry_points.txt
fede-0.1.1.dist-info/LICENSE
fede-0.1.1.dist-info/WHEEL
fede-0.1.1.dist-info/METADATA
fede-0.1.1.dist-info/RECORD
